qtmodernredux6/__init__.py
qtmodernredux6/qtmodernredux.py
qtmodernredux6/apl_style/__init__.py
qtmodernredux6/apl_style/style.py
qtmodernredux6/apl_style/widgetstyle/__init__.py
qtmodernredux6/apl_style/widgetstyle/base.py
qtmodernredux6/apl_style/widgetstyle/checkbox.py
qtmodernredux6/apl_style/widgetstyle/combobox.py
qtmodernredux6/apl_style/widgetstyle/constants.py
qtmodernredux6/apl_style/widgetstyle/groupbox.py
qtmodernredux6/apl_style/widgetstyle/headerview.py
qtmodernredux6/apl_style/widgetstyle/lineedit.py
qtmodernredux6/apl_style/widgetstyle/progressbar.py
qtmodernredux6/apl_style/widgetstyle/pushbutton.py
qtmodernredux6/apl_style/widgetstyle/radiobutton.py
qtmodernredux6/apl_style/widgetstyle/scrollarea.py
qtmodernredux6/apl_style/widgetstyle/scrollbar.py
qtmodernredux6/apl_style/widgetstyle/slider.py
qtmodernredux6/apl_style/widgetstyle/spinbox.py
qtmodernredux6/apl_style/widgetstyle/splitter.py
qtmodernredux6/apl_style/widgetstyle/tableview.py
qtmodernredux6/apl_style/widgetstyle/tabwidget.py
qtmodernredux6/apl_style/widgetstyle/tabwidget_titlebar.py
qtmodernredux6/apl_style/widgetstyle/toolbar.py
qtmodernredux6/apl_style/widgetstyle/treeview.py
qtmodernredux6/apl_style/windowstyle/__init__.py
qtmodernredux6/apl_style/windowstyle/buttons.py
qtmodernredux6/apl_style/windowstyle/constants.py
qtmodernredux6/apl_style/windowstyle/frame.py
qtmodernredux6/resources/__init__.py
qtmodernredux6/resources/qt_resources.py
qtmodernredux6/windowstyle/__init__.py
qtmodernredux6/windowstyle/modernwindow.py
qtmodernredux6/windowstyle/tabfilter.py
qtmodernredux6/windowstyle/windowframe.py
qtmodernredux6/windowstyle/windowresizer.py
qtmodernredux6/windowstyle/windowtitlelabel.py
QtModernRedux6-0.9.15.dist-info/LICENSE
QtModernRedux6-0.9.15.dist-info/METADATA
QtModernRedux6-0.9.15.dist-info/WHEEL
QtModernRedux6-0.9.15.dist-info/top_level.txt
QtModernRedux6-0.9.15.dist-info/RECORD
