Metadata-Version: 2.1
Name: QtModernRedux6
Version: 0.9.15
Summary: a modern UI style for Python 3.x / PySide6 applications
Home-page: https://github.com/robertkist/qtmodernredux
Author: Robert Kist
Author-email: kr@robertkist.com
Classifier: Programming Language :: Python :: 3
Classifier: License :: OSI Approved :: MIT License
Classifier: Operating System :: OS Independent
Classifier: Programming Language :: Python :: 3.9
Requires-Python: >=3.9.4
License-File: LICENSE
Requires-Dist: PySide6 (>=6.3.0)
